{
  "dc_creator_sm": [
    "Sanson, Nicolas, 1600-1667"
  ],
  "dc_description_s": "Relief shown pictorially. From A. Phe\u0301rote\u0301e de la Croix, Algemeene Weereld-beschryving ... Op een gantsch nieuwe, zeerklaere ordre in 't Fransch beschreeven. Place names primarily in French. Shows California as an island.",
  "dc_format_s": "TIFF",
  "dc_identifier_s": "ark:/88435/6t053j496",
  "dc_language_s": "Dutch; Flemish",
  "dc_publisher_s": "[Amsterdam?] : [publisher not identified], [1705?]",
  "dc_rights_s": "Public",
  "dc_subject_sm": [
    "California,Maps,Early works to 1800",
    "Mexico,Maps,Early works to 1800",
    "West (U.S.),Maps,Early works to 1800"
  ],
  "dc_title_s": "T gebiedt van Guadalajara, Niew Mexico, en Californie, enz",
  "dc_type_s": "Image",
  "dct_isPartOf_sm": [],
  "dct_issued_s": "",
  "dct_provenance_s": "Princeton",
  "dct_references_s": "{\"http://schema.org/url\":\"https://catalog.princeton.edu/catalog/7917734\",\"http://schema.org/downloadUrl\":\"https://figgy.princeton.edu/downloads/3636f122-ccae-496f-8b56-6755050a49dc/file/c838cd19-518a-4ced-a265-8fd4d45e49c1\",\"http://schema.org/thumbnailUrl\":\"https://figgy.princeton.edu/downloads/3636f122-ccae-496f-8b56-6755050a49dc/file/110300dd-6206-4709-b427-537cfdf83235\",\"http://iiif.io/api/image\":\"https://libimages1.princeton.edu/loris/figgy_prod/ea%2F20%2Fd0%2Fea20d024c03e46ec85fb4d77663f572c%2Fintermediate_file.jp2/info.json\",\"http://iiif.io/api/presentation#manifest\":\"https://figgy.princeton.edu/concern/scanned_maps/ae035e26-1954-4c92-80df-6d2627f38aef/manifest\"}",
  "dct_source_sm": [],
  "dct_spatial_sm": [
    "Mexico",
    "West (U.S.)"
  ],
  "dct_temporal_sm": [
    "1705"
  ],
  "geoblacklight_version": 1.0,
  "layer_geom_type_s": "Image",
  "layer_id_s": "public-figgy:p-3636f122-ccae-496f-8b56-6755050a49dc",
  "layer_modified_dt": "2019-02-28T00:22:29Z",
  "layer_slug_s": "princeton-6t053j496",
  "nyu_addl_format_sm": [
    "TIFF"
  ],
  "solr_geom": "ENVELOPE(-129.5094, -96.0066, 48.4228, 19.0115)",
  "solr_year_i": 1705.0,
  "uuid": "princeton-6t053j496"
}