{
  "dc_creator_sm": [],
  "dc_description_s": "Shows streets, buildings and city wall. Includes legend.",
  "dc_format_s": "TIFF",
  "dc_identifier_s": "ark:/88435/c534fr364",
  "dc_language_s": "English",
  "dc_publisher_s": "[New York : Common Council, 1851] ([New York] : Geo. Hayward)",
  "dc_rights_s": "Public",
  "dc_subject_sm": [
    "New York (N.Y.),Maps,Early works to 1800"
  ],
  "dc_title_s": "New Yorke, 1695",
  "dc_type_s": "Image",
  "dct_isPartOf_sm": [],
  "dct_issued_s": "",
  "dct_provenance_s": "Princeton",
  "dct_references_s": "{\"http://schema.org/url\":\"https://catalog.princeton.edu/catalog/6166344\",\"http://schema.org/downloadUrl\":\"https://figgy.princeton.edu/downloads/951c6854-6559-480e-84bd-330327defd1d/file/231d72ed-a258-4897-8947-9f5110dbea64\",\"http://schema.org/thumbnailUrl\":\"https://figgy.princeton.edu/downloads/951c6854-6559-480e-84bd-330327defd1d/file/50247a05-e58a-47e0-8e0a-536d74f094f7\",\"http://iiif.io/api/image\":\"https://libimages1.princeton.edu/loris/figgy_prod/22%2Fe2%2Fb0%2F22e2b0ebf2fb4e229aeb427e93c51013%2Fintermediate_file.jp2/info.json\",\"http://iiif.io/api/presentation#manifest\":\"https://figgy.princeton.edu/concern/scanned_maps/230c7870-80c0-43b0-912d-5598bbe431d3/manifest\"}",
  "dct_source_sm": [],
  "dct_spatial_sm": [
    "New York"
  ],
  "dct_temporal_sm": [
    "1851"
  ],
  "geoblacklight_version": "1.0",
  "layer_geom_type_s": "Image",
  "layer_id_s": "public-figgy:p-951c6854-6559-480e-84bd-330327defd1d",
  "layer_modified_dt": "2019-02-28T00:22:29Z",
  "layer_slug_s": "princeton-c534fr364",
  "nyu_addl_format_sm": [
    "TIFF"
  ],
  "solr_geom": "ENVELOPE(-74.0195340413, -74.0004367131, 40.7115625752, 40.6996880856)",
  "solr_year_i": "1851.0",
  "uuid": "princeton-c534fr364"
}