{
  "dc_creator_sm": [
    "Sanborn Map Company"
  ],
  "dc_description_s": "\"Dec. 1886.\" Includes key, streets and specials index, and text. North oriented towards upper right.",
  "dc_format_s": "TIFF",
  "dc_identifier_s": "ark:/88435/th83m082b",
  "dc_language_s": "English",
  "dc_publisher_s": "New York : Sanborn Map & Publishing Co., Limited, 1886.",
  "dc_rights_s": "Public",
  "dc_subject_sm": [
    "Real property,New Jersey,Atlantic City,Maps",
    "Atlantic City (N.J.),Maps"
  ],
  "dc_title_s": "Atlantic City, New Jersey (Sheet 17)",
  "dc_type_s": "Image",
  "dct_isPartOf_sm": [],
  "dct_issued_s": "",
  "dct_provenance_s": "Princeton",
  "dct_references_s": "{\"http://schema.org/url\":\"https://catalog.princeton.edu/catalog/5165864\",\"http://schema.org/downloadUrl\":\"https://figgy.princeton.edu/downloads/c124032d-b925-4d13-8cae-a7c58d35094e/file/59ff956d-0202-49a8-b924-b3e2810f7824\",\"http://schema.org/thumbnailUrl\":\"https://figgy.princeton.edu/downloads/c124032d-b925-4d13-8cae-a7c58d35094e/file/dfe3b380-01a5-401a-9215-84cf37598a13\",\"http://iiif.io/api/image\":\"https://libimages1.princeton.edu/loris/figgy_prod/6e%2F55%2Fbc%2F6e55bc85cea74ec494ea7134069b6c08%2Fintermediate_file.jp2/info.json\",\"http://iiif.io/api/presentation#manifest\":\"https://figgy.princeton.edu/concern/scanned_maps/34b2e131-a486-4de2-87aa-6e8994080f68/manifest\"}",
  "dct_source_sm": [],
  "dct_spatial_sm": [
    "New Jersey"
  ],
  "dct_temporal_sm": [
    "1886"
  ],
  "geoblacklight_version": 1.0,
  "layer_geom_type_s": "Image",
  "layer_id_s": "public-figgy:p-c124032d-b925-4d13-8cae-a7c58d35094e",
  "layer_modified_dt": "2019-02-28T00:22:29Z",
  "layer_slug_s": "princeton-th83m082b",
  "nyu_addl_format_sm": [
    "TIFF"
  ],
  "solr_geom": "ENVELOPE(-74.498, -74.408, 39.417, 39.342)",
  "solr_year_i": 1886.0,
  "uuid": "princeton-th83m082b"
}