{
  "dc_creator_sm": [
    "Sanborn Map Company"
  ],
  "dc_description_s": "Includes key, key map, streets and specials index, and text. \"5119.\" South Orange Village and Township are identical and coextensive with South Orange, a census desig. place; P.O. name South Orange. cf. Rand McNally comm. atlas, 1991. Historic Maps copy has sheets 1-7, 31-32, 41-44, and 46-66 of South Orange Village series, showing South Orange Township.",
  "dc_format_s": "TIFF",
  "dc_identifier_s": "ark:/88435/1v53jz98s",
  "dc_language_s": "English",
  "dc_publisher_s": "New York : Sanborn Map Co., 1912.",
  "dc_rights_s": "Public",
  "dc_subject_sm": [
    "Real property,New Jersey,South Orange,Maps",
    "South Orange (N.J.),Maps"
  ],
  "dc_title_s": "Insurance maps of South Orange Village, including South Orange and Millburn Townships, New Jersey (Sheet 53)",
  "dc_type_s": "Image",
  "dct_isPartOf_sm": [],
  "dct_issued_s": "",
  "dct_provenance_s": "Princeton",
  "dct_references_s": "{\"http://schema.org/url\":\"https://catalog.princeton.edu/catalog/5476025\",\"http://schema.org/downloadUrl\":\"https://figgy.princeton.edu/downloads/a42b6964-56b4-4fe9-ab9c-0d2fa2f30280/file/6ed191eb-fb94-4af2-93c5-47cefd9bf4cf\",\"http://schema.org/thumbnailUrl\":\"https://figgy.princeton.edu/downloads/a42b6964-56b4-4fe9-ab9c-0d2fa2f30280/file/8744a7b2-952f-4d92-911b-9536f6878b19\",\"http://iiif.io/api/image\":\"https://libimages1.princeton.edu/loris/figgy_prod/32%2Fc4%2Fdc%2F32c4dc3d825246d9b07d70c4a0d062f7%2Fintermediate_file.jp2/info.json\",\"http://iiif.io/api/presentation#manifest\":\"https://figgy.princeton.edu/concern/scanned_maps/a1b64162-6547-4db4-8b3c-8654636a4d94/manifest\"}",
  "dct_source_sm": [],
  "dct_spatial_sm": [
    "New Jersey"
  ],
  "dct_temporal_sm": [
    "1912"
  ],
  "geoblacklight_version": "1.0",
  "layer_geom_type_s": "Image",
  "layer_id_s": "public-figgy:p-a42b6964-56b4-4fe9-ab9c-0d2fa2f30280",
  "layer_modified_dt": "2019-02-28T00:22:29Z",
  "layer_slug_s": "princeton-1v53jz98s",
  "nyu_addl_format_sm": [
    "TIFF"
  ],
  "solr_geom": "ENVELOPE(-74.283427, -74.234841, 40.762314, 40.735601)",
  "solr_year_i": "1912",
  "uuid": "princeton-1v53jz98s"
}